CONTRIB
LICENSE
MANIFEST.in
README.rst
TODO
distribute_setup.py
setup.py
Volt.egg-info/PKG-INFO
Volt.egg-info/SOURCES.txt
Volt.egg-info/dependency_links.txt
Volt.egg-info/entry_points.txt
Volt.egg-info/not-zip-safe
Volt.egg-info/requires.txt
Volt.egg-info/top_level.txt
docs/build/doctrees/changelog.doctree
docs/build/doctrees/contributing.doctree
docs/build/doctrees/environment.pickle
docs/build/doctrees/extension.doctree
docs/build/doctrees/help.doctree
docs/build/doctrees/index.doctree
docs/build/doctrees/internals.doctree
docs/build/doctrees/introduction.doctree
docs/build/doctrees/quickstart.doctree
docs/build/html/.buildinfo
docs/build/html/changelog.html
docs/build/html/contributing.html
docs/build/html/extension.html
docs/build/html/genindex.html
docs/build/html/help.html
docs/build/html/index.html
docs/build/html/internals.html
docs/build/html/introduction.html
docs/build/html/objects.inv
docs/build/html/quickstart.html
docs/build/html/search.html
docs/build/html/searchindex.js
docs/build/html/_sources/changelog.txt
docs/build/html/_sources/contributing.txt
docs/build/html/_sources/extension.txt
docs/build/html/_sources/help.txt
docs/build/html/_sources/index.txt
docs/build/html/_sources/internals.txt
docs/build/html/_sources/introduction.txt
docs/build/html/_sources/quickstart.txt
docs/build/html/_static/agogo.css
docs/build/html/_static/ajax-loader.gif
docs/build/html/_static/alert_info_32.png
docs/build/html/_static/alert_warning_32.png
docs/build/html/_static/basic.css
docs/build/html/_static/bg-page.png
docs/build/html/_static/bgfooter.png
docs/build/html/_static/bgtop.png
docs/build/html/_static/bullet_orange.png
docs/build/html/_static/comment-bright.png
docs/build/html/_static/comment-close.png
docs/build/html/_static/comment.png
docs/build/html/_static/default.css
docs/build/html/_static/doctools.js
docs/build/html/_static/down-pressed.png
docs/build/html/_static/down.png
docs/build/html/_static/file.png
docs/build/html/_static/haiku.css
docs/build/html/_static/jquery.js
docs/build/html/_static/minus.png
docs/build/html/_static/nature.css
docs/build/html/_static/plus.png
docs/build/html/_static/pygments.css
